latex_calculator_mcp/__init__.py
latex_calculator_mcp/server.py
latex_calculator_mcp-2.0.1.dist-info/METADATA
latex_calculator_mcp-2.0.1.dist-info/WHEEL
latex_calculator_mcp-2.0.1.dist-info/entry_points.txt
latex_calculator_mcp-2.0.1.dist-info/licenses/LICENSE
latex_calculator_mcp-2.0.1.dist-info/RECORD
