Metadata-Version: 2.4
Name: latex-calculator-mcp
Version: 2.0.1
Summary: LaTeX公式计算MCP服务，支持基础运算、三角函数、反三角函数、度分秒(DMS)格式
Project-URL: Homepage, https://github.com/yourusername/latex-calculator-mcp
Project-URL: Repository, https://github.com/yourusername/latex-calculator-mcp
Project-URL: Documentation, https://github.com/yourusername/latex-calculator-mcp#readme
Project-URL: Issues, https://github.com/yourusername/latex-calculator-mcp/issues
Author-email: pypypywy <1992541488@qq.com>
License-Expression: MIT
License-File: LICENSE
Keywords: calculator,degree-minute-second,dms,latex,math,mcp,trigonometry
Classifier: Development Status :: 4 - Beta
Classifier: Intended Audience :: Developers
Classifier: Intended Audience :: Science/Research
Classifier: License :: OSI Approved :: MIT License
Classifier: Operating System :: OS Independent
Classifier: Programming Language :: Python :: 3
Classifier: Programming Language :: Python :: 3.8
Classifier: Programming Language :: Python :: 3.9
Classifier: Programming Language :: Python :: 3.10
Classifier: Programming Language :: Python :: 3.11
Classifier: Programming Language :: Python :: 3.12
Classifier: Topic :: Scientific/Engineering :: Mathematics
Requires-Python: >=3.8
Requires-Dist: fastmcp
Requires-Dist: latex2sympy2
Requires-Dist: mcp
Requires-Dist: sympy
